cli_app/__init__.py
cli_app/__main__.py
cli_app/cli.py
cli_app/main.py
printlinter/__init__.py
printlinter/classes.py
printlinter/config.py
printlinter/ignored_processing.py
printlinter/parser.py
printlinter/visitor.py
printlinter-0.3.2.dist-info/entry_points.txt
printlinter-0.3.2.dist-info/LICENSE.md
printlinter-0.3.2.dist-info/WHEEL
printlinter-0.3.2.dist-info/METADATA
printlinter-0.3.2.dist-info/RECORD
