Metadata-Version: 2.1
Name: printlinter
Version: 0.3.2
Summary: print linter to know where is the test print
License: EUPL v1.2
Author: ulysse
Author-email: ulysse.chosson@obspm.fr
Requires-Python: >=3.10,<4.0
Classifier: License :: Other/Proprietary License
Classifier: Programming Language :: Python :: 3
Classifier: Programming Language :: Python :: 3.10
Classifier: Programming Language :: Python :: 3.11
Requires-Dist: pyyaml (>=6.0.1,<7.0.0)
Requires-Dist: rich (>=12.5.1,<13.0.0)
Requires-Dist: toml (>=0.10.2,<0.11.0)
Requires-Dist: typer (>=0.7.0,<0.8.0)
